cl/tradeentry/__init__.py
tradeentry-0.0.1.dist-info/LICENSE
tradeentry-0.0.1.dist-info/METADATA
tradeentry-0.0.1.dist-info/WHEEL
tradeentry-0.0.1.dist-info/top_level.txt
tradeentry-0.0.1.dist-info/RECORD
