Metadata-Version: 2.1
Name: tradeentry
Version: 0.0.1
Summary: Trade entry from natural language for capital markets using LLMs
Home-page: https://github.com/compatibl/tradeentry
Author: The Project Contributors
License: Apache Software License
Project-URL: Source Code, https://github.com/compatibl/tradeentry
Classifier: Development Status :: 3 - Alpha
Classifier: Intended Audience :: Developers
Classifier: Intended Audience :: Science/Research
Classifier: Intended Audience :: Financial and Insurance Industry
Classifier: Topic :: Software Development
Classifier: Topic :: Scientific/Engineering
Classifier: License :: OSI Approved :: Apache Software License
Classifier: Programming Language :: Python :: 3.10
Classifier: Programming Language :: Python :: 3.11
Classifier: Programming Language :: Python :: 3.12
Classifier: Operating System :: OS Independent
License-File: LICENSE
Requires-Dist: runtime >=0.0.1
